searchly_tables/__init__.py
searchly_tables/apps.py
searchly_tables/tables.py
searchly_tables/tests.py
searchly_tables/migrations/__init__.py
django_searchly_tables-0.1.dist-info/LICENSE
django_searchly_tables-0.1.dist-info/METADATA
django_searchly_tables-0.1.dist-info/WHEEL
django_searchly_tables-0.1.dist-info/top_level.txt
django_searchly_tables-0.1.dist-info/RECORD
