Metadata-Version: 2.1
Name: django-searchly-tables
Version: 0.1
Summary: A simple Django app that adds search and sort to HTML tables.
Home-page: https://github.com/peterschueler/django-searchly-tables
Author: Peter Schueler
Author-email: peter@orangemirrorentertainment.com
License: MIT License
Platform: UNKNOWN
Classifier: Environment :: Web Environment
Classifier: Framework :: Django
Classifier: Framework :: Django :: 2.1
Classifier: Intended Audience :: Developers
Classifier: License :: OSI Approved :: MIT License
Classifier: Operating System :: OS Independent
Classifier: Programming Language :: Python
Classifier: Programming Language :: Python :: 3.7
Classifier: Topic :: Internet :: WWW/HTTP
Classifier: Topic :: Internet :: WWW/HTTP :: Dynamic Content
